{
  "generated_at": "2026-05-24T17:53:52.387732+00:00",
  "as_of": "2026-05-24",
  "training_window_years": 3,
  "horizon_days": 30,
  "concentration_diagnostic": {
    "concentrated": false,
    "dominant_signal": "ACHAT",
    "ratio": 0.3043,
    "n": 46,
    "threshold": 0.7
  },
  "liquidity_diagnostics": [
    {
      "ticker": "ABJC_ci",
      "illiquid_ratio": 0.1773,
      "rows_raw": 3571,
      "rows_kept": 2938,
      "excluded": false
    },
    {
      "ticker": "BICB_bj",
      "illiquid_ratio": 0.0468,
      "rows_raw": 278,
      "rows_kept": 265,
      "excluded": false
    },
    {
      "ticker": "BICC_ci",
      "illiquid_ratio": 0.2468,
      "rows_raw": 3432,
      "rows_kept": 2585,
      "excluded": false
    },
    {
      "ticker": "BNBC_ci",
      "illiquid_ratio": 0.2054,
      "rows_raw": 3058,
      "rows_kept": 2430,
      "excluded": false
    },
    {
      "ticker": "BOAB_bj",
      "illiquid_ratio": 0.3242,
      "rows_raw": 4071,
      "rows_kept": 2751,
      "excluded": false
    },
    {
      "ticker": "BOABF_bf",
      "illiquid_ratio": 0.174,
      "rows_raw": 3459,
      "rows_kept": 2857,
      "excluded": false
    },
    {
      "ticker": "BOAC_ci",
      "illiquid_ratio": 0.1717,
      "rows_raw": 3553,
      "rows_kept": 2943,
      "excluded": false
    },
    {
      "ticker": "BOAM_ml",
      "illiquid_ratio": 0.1039,
      "rows_raw": 2540,
      "rows_kept": 2276,
      "excluded": false
    },
    {
      "ticker": "BOAN_ne",
      "illiquid_ratio": 0.2216,
      "rows_raw": 3940,
      "rows_kept": 3067,
      "excluded": false
    },
    {
      "ticker": "BOAS_sn",
      "illiquid_ratio": 0.1232,
      "rows_raw": 2930,
      "rows_kept": 2569,
      "excluded": false
    },
    {
      "ticker": "CABC_ci",
      "illiquid_ratio": 0.2259,
      "rows_raw": 3147,
      "rows_kept": 2436,
      "excluded": false
    },
    {
      "ticker": "CBIBF_bf",
      "illiquid_ratio": 0.2474,
      "rows_raw": 2300,
      "rows_kept": 1731,
      "excluded": false
    },
    {
      "ticker": "CFAC_ci",
      "illiquid_ratio": 0.2187,
      "rows_raw": 3142,
      "rows_kept": 2455,
      "excluded": false
    },
    {
      "ticker": "CIEC_ci",
      "illiquid_ratio": 0.1786,
      "rows_raw": 4273,
      "rows_kept": 3510,
      "excluded": false
    },
    {
      "ticker": "ECOC_ci",
      "illiquid_ratio": 0.0964,
      "rows_raw": 2167,
      "rows_kept": 1958,
      "excluded": false
    },
    {
      "ticker": "ETIT_tg",
      "illiquid_ratio": 0.6063,
      "rows_raw": 2964,
      "rows_kept": 1167,
      "excluded": true
    },
    {
      "ticker": "FTSC_ci",
      "illiquid_ratio": 0.1565,
      "rows_raw": 4141,
      "rows_kept": 3493,
      "excluded": false
    },
    {
      "ticker": "LNBB_bj",
      "illiquid_ratio": 0.1206,
      "rows_raw": 373,
      "rows_kept": 328,
      "excluded": false
    },
    {
      "ticker": "NEIC_ci",
      "illiquid_ratio": 0.2802,
      "rows_raw": 2284,
      "rows_kept": 1644,
      "excluded": false
    },
    {
      "ticker": "NSBC_ci",
      "illiquid_ratio": 0.1175,
      "rows_raw": 2145,
      "rows_kept": 1893,
      "excluded": false
    },
    {
      "ticker": "NTLC_ci",
      "illiquid_ratio": 0.2655,
      "rows_raw": 3137,
      "rows_kept": 2304,
      "excluded": false
    },
    {
      "ticker": "ONTBF_bf",
      "illiquid_ratio": 0.1571,
      "rows_raw": 3927,
      "rows_kept": 3310,
      "excluded": false
    },
    {
      "ticker": "ORAC_ci",
      "illiquid_ratio": 0.0941,
      "rows_raw": 882,
      "rows_kept": 799,
      "excluded": false
    },
    {
      "ticker": "ORGT_tg",
      "illiquid_ratio": 0.2097,
      "rows_raw": 1707,
      "rows_kept": 1349,
      "excluded": false
    },
    {
      "ticker": "PALC_ci",
      "illiquid_ratio": 0.099,
      "rows_raw": 2870,
      "rows_kept": 2586,
      "excluded": false
    },
    {
      "ticker": "PRSC_ci",
      "illiquid_ratio": 0.2493,
      "rows_raw": 2150,
      "rows_kept": 1614,
      "excluded": false
    },
    {
      "ticker": "SAFC_ci",
      "illiquid_ratio": 0.2892,
      "rows_raw": 1352,
      "rows_kept": 961,
      "excluded": false
    },
    {
      "ticker": "SCRC_ci",
      "illiquid_ratio": 0.1329,
      "rows_raw": 2377,
      "rows_kept": 2061,
      "excluded": false
    },
    {
      "ticker": "SDCC_ci",
      "illiquid_ratio": 0.2207,
      "rows_raw": 3666,
      "rows_kept": 2857,
      "excluded": false
    },
    {
      "ticker": "SDSC_ci",
      "illiquid_ratio": 0.1941,
      "rows_raw": 3658,
      "rows_kept": 2948,
      "excluded": false
    },
    {
      "ticker": "SEMC_ci",
      "illiquid_ratio": 0.0098,
      "rows_raw": 102,
      "rows_kept": 101,
      "excluded": false
    },
    {
      "ticker": "SGBC_ci",
      "illiquid_ratio": 0.1577,
      "rows_raw": 4154,
      "rows_kept": 3499,
      "excluded": false
    },
    {
      "ticker": "SHEC_ci",
      "illiquid_ratio": 0.2122,
      "rows_raw": 3972,
      "rows_kept": 3129,
      "excluded": false
    },
    {
      "ticker": "SIBC_ci",
      "illiquid_ratio": 0.0914,
      "rows_raw": 2451,
      "rows_kept": 2227,
      "excluded": false
    },
    {
      "ticker": "SICC_ci",
      "illiquid_ratio": 0.2998,
      "rows_raw": 1611,
      "rows_kept": 1128,
      "excluded": false
    },
    {
      "ticker": "SIVC_ci",
      "illiquid_ratio": 0.2863,
      "rows_raw": 3748,
      "rows_kept": 2675,
      "excluded": false
    },
    {
      "ticker": "SLBC_ci",
      "illiquid_ratio": 0.3346,
      "rows_raw": 2379,
      "rows_kept": 1583,
      "excluded": false
    },
    {
      "ticker": "SMBC_ci",
      "illiquid_ratio": 0.2232,
      "rows_raw": 3127,
      "rows_kept": 2429,
      "excluded": false
    },
    {
      "ticker": "SNTS_sn",
      "illiquid_ratio": 0.2547,
      "rows_raw": 4633,
      "rows_kept": 3453,
      "excluded": false
    },
    {
      "ticker": "SOGC_ci",
      "illiquid_ratio": 0.1593,
      "rows_raw": 4112,
      "rows_kept": 3457,
      "excluded": false
    },
    {
      "ticker": "SPHC_ci",
      "illiquid_ratio": 0.1651,
      "rows_raw": 4276,
      "rows_kept": 3570,
      "excluded": false
    },
    {
      "ticker": "STAC_ci",
      "illiquid_ratio": 0.3034,
      "rows_raw": 2205,
      "rows_kept": 1536,
      "excluded": false
    },
    {
      "ticker": "STBC_ci",
      "illiquid_ratio": 0.2631,
      "rows_raw": 3280,
      "rows_kept": 2417,
      "excluded": false
    },
    {
      "ticker": "TTLC_ci",
      "illiquid_ratio": 0.1537,
      "rows_raw": 3651,
      "rows_kept": 3090,
      "excluded": false
    },
    {
      "ticker": "TTLS_sn",
      "illiquid_ratio": 0.1347,
      "rows_raw": 2732,
      "rows_kept": 2364,
      "excluded": false
    },
    {
      "ticker": "UNLC_ci",
      "illiquid_ratio": 0.3786,
      "rows_raw": 1746,
      "rows_kept": 1085,
      "excluded": false
    },
    {
      "ticker": "UNXC_ci",
      "illiquid_ratio": 0.1532,
      "rows_raw": 3369,
      "rows_kept": 2853,
      "excluded": false
    }
  ],
  "signals": {
    "ABJC_ci": {
      "ticker": "ABJC_ci",
      "last_price": 2875.0,
      "last_date": "2026-05-22",
      "signal": "ACHAT FORT",
      "confidence": "Haute",
      "target_30d": 3843.2,
      "trend": "UP",
      "yhat": 3843.2,
      "yhat_lower": 3646.66,
      "yhat_upper": 4029.21,
      "train_start": "2023-05-24",
      "train_end": "2026-05-22",
      "train_rows": 687,
      "train_annualized_return": 0.3384
    },
    "BICB_bj": {
      "ticker": "BICB_bj",
      "last_price": 5225.0,
      "last_date": "2026-05-22",
      "signal": "NEUTRE",
      "confidence": "Haute",
      "target_30d": 5378.71,
      "trend": "UP",
      "yhat": 5378.71,
      "yhat_lower": 5293.99,
      "yhat_upper": 5456.69,
      "train_start": "2025-04-28",
      "train_end": "2026-05-22",
      "train_rows": 265,
      "train_annualized_return": -0.063
    },
    "BICC_ci": {
      "ticker": "BICC_ci",
      "last_price": 27000.0,
      "last_date": "2026-05-22",
      "signal": "ACHAT",
      "confidence": "Haute",
      "target_30d": 28407.14,
      "trend": "UP",
      "yhat": 28407.14,
      "yhat_lower": 27516.25,
      "yhat_upper": 29269.92,
      "train_start": "2023-05-25",
      "train_end": "2026-05-22",
      "train_rows": 602,
      "train_annualized_return": 0.6089
    },
    "BNBC_ci": {
      "ticker": "BNBC_ci",
      "last_price": 1500.0,
      "last_date": "2026-05-22",
      "signal": "ACHAT",
      "confidence": "Moyenne",
      "target_30d": 1595.63,
      "trend": "UP",
      "yhat": 1595.63,
      "yhat_lower": 1443.79,
      "yhat_upper": 1742.05,
      "train_start": "2023-05-30",
      "train_end": "2026-05-22",
      "train_rows": 691,
      "train_annualized_return": -0.0827
    },
    "BOAB_bj": {
      "ticker": "BOAB_bj",
      "last_price": 8950.0,
      "last_date": "2026-05-22",
      "signal": "ACHAT",
      "confidence": "Haute",
      "target_30d": 9265.99,
      "trend": "UP",
      "yhat": 9265.99,
      "yhat_lower": 9010.58,
      "yhat_upper": 9495.64,
      "train_start": "2023-05-24",
      "train_end": "2026-05-22",
      "train_rows": 713,
      "train_annualized_return": 0.4611
    },
    "BOABF_bf": {
      "ticker": "BOABF_bf",
      "last_price": 5440.0,
      "last_date": "2026-05-22",
      "signal": "ACHAT",
      "confidence": "Haute",
      "target_30d": 5787.24,
      "trend": "UP",
      "yhat": 5787.24,
      "yhat_lower": 5610.64,
      "yhat_upper": 5969.65,
      "train_start": "2023-05-24",
      "train_end": "2026-05-22",
      "train_rows": 714,
      "train_annualized_return": 0.2712
    },
    "BOAC_ci": {
      "ticker": "BOAC_ci",
      "last_price": 8870.0,
      "last_date": "2026-05-22",
      "signal": "NEUTRE",
      "confidence": "Haute",
      "target_30d": 8940.89,
      "trend": "UP",
      "yhat": 8940.89,
      "yhat_lower": 8690.23,
      "yhat_upper": 9191.51,
      "train_start": "2023-05-24",
      "train_end": "2026-05-22",
      "train_rows": 734,
      "train_annualized_return": 0.5263
    },
    "BOAM_ml": {
      "ticker": "BOAM_ml",
      "last_price": 4990.0,
      "last_date": "2026-05-22",
      "signal": "NEUTRE",
      "confidence": "Haute",
      "target_30d": 4951.58,
      "trend": "DOWN",
      "yhat": 4951.58,
      "yhat_lower": 4810.15,
      "yhat_upper": 5101.32,
      "train_start": "2023-05-24",
      "train_end": "2026-05-22",
      "train_rows": 715,
      "train_annualized_return": 0.7392
    },
    "BOAN_ne": {
      "ticker": "BOAN_ne",
      "last_price": 3730.0,
      "last_date": "2026-05-22",
      "signal": "VENTE FORTE",
      "confidence": "Haute",
      "target_30d": 3082.77,
      "trend": "DOWN",
      "yhat": 3082.77,
      "yhat_lower": 2877.13,
      "yhat_upper": 3284.7,
      "train_start": "2023-05-24",
      "train_end": "2026-05-22",
      "train_rows": 729,
      "train_annualized_return": 0.0218
    },
    "BOAS_sn": {
      "ticker": "BOAS_sn",
      "last_price": 7990.0,
      "last_date": "2026-05-22",
      "signal": "VENTE",
      "confidence": "Haute",
      "target_30d": 7678.25,
      "trend": "DOWN",
      "yhat": 7678.25,
      "yhat_lower": 7456.54,
      "yhat_upper": 7907.04,
      "train_start": "2023-05-24",
      "train_end": "2026-05-22",
      "train_rows": 693,
      "train_annualized_return": 0.6452
    },
    "CABC_ci": {
      "ticker": "CABC_ci",
      "last_price": 3585.0,
      "last_date": "2026-05-22",
      "signal": "ACHAT FORT",
      "confidence": "Haute",
      "target_30d": 4138.96,
      "trend": "UP",
      "yhat": 4138.96,
      "yhat_lower": 3942.09,
      "yhat_upper": 4326.67,
      "train_start": "2023-05-24",
      "train_end": "2026-05-22",
      "train_rows": 667,
      "train_annualized_return": 0.5088
    },
    "CBIBF_bf": {
      "ticker": "CBIBF_bf",
      "last_price": 20700.0,
      "last_date": "2026-05-22",
      "signal": "NEUTRE",
      "confidence": "Haute",
      "target_30d": 20142.23,
      "trend": "DOWN",
      "yhat": 20142.23,
      "yhat_lower": 19636.7,
      "yhat_upper": 20579.73,
      "train_start": "2023-05-26",
      "train_end": "2026-05-22",
      "train_rows": 676,
      "train_annualized_return": 0.3798
    },
    "CFAC_ci": {
      "ticker": "CFAC_ci",
      "last_price": 1485.0,
      "last_date": "2026-05-22",
      "signal": "ACHAT",
      "confidence": "Moyenne",
      "target_30d": 1576.68,
      "trend": "UP",
      "yhat": 1576.68,
      "yhat_lower": 1444.86,
      "yhat_upper": 1706.92,
      "train_start": "2023-05-24",
      "train_end": "2026-05-22",
      "train_rows": 686,
      "train_annualized_return": 0.2616
    },
    "CIEC_ci": {
      "ticker": "CIEC_ci",
      "last_price": 4040.0,
      "last_date": "2026-05-22",
      "signal": "VENTE",
      "confidence": "Haute",
      "target_30d": 3734.99,
      "trend": "DOWN",
      "yhat": 3734.99,
      "yhat_lower": 3624.88,
      "yhat_upper": 3839.13,
      "train_start": "2023-05-24",
      "train_end": "2026-05-22",
      "train_rows": 685,
      "train_annualized_return": 0.2612
    },
    "ECOC_ci": {
      "ticker": "ECOC_ci",
      "last_price": 16200.0,
      "last_date": "2026-05-12",
      "signal": "ACHAT",
      "confidence": "Haute",
      "target_30d": 16726.78,
      "trend": "UP",
      "yhat": 16726.78,
      "yhat_lower": 16326.01,
      "yhat_upper": 17136.19,
      "train_start": "2023-05-24",
      "train_end": "2026-05-12",
      "train_rows": 713,
      "train_annualized_return": 0.4387
    },
    "FTSC_ci": {
      "ticker": "FTSC_ci",
      "last_price": 2280.0,
      "last_date": "2026-05-22",
      "signal": "ACHAT",
      "confidence": "Basse",
      "target_30d": 2367.77,
      "trend": "UP",
      "yhat": 2367.77,
      "yhat_lower": 2005.88,
      "yhat_upper": 2758.1,
      "train_start": "2023-05-24",
      "train_end": "2026-05-22",
      "train_rows": 722,
      "train_annualized_return": 0.2475
    },
    "LNBB_bj": {
      "ticker": "LNBB_bj",
      "last_price": 3860.0,
      "last_date": "2026-05-22",
      "signal": "NEUTRE",
      "confidence": "Haute",
      "target_30d": 3897.68,
      "trend": "UP",
      "yhat": 3897.68,
      "yhat_lower": 3791.74,
      "yhat_upper": 4011.94,
      "train_start": "2024-12-13",
      "train_end": "2026-05-22",
      "train_rows": 328,
      "train_annualized_return": -0.1827
    },
    "NEIC_ci": {
      "ticker": "NEIC_ci",
      "last_price": 1990.0,
      "last_date": "2026-05-22",
      "signal": "NEUTRE",
      "confidence": "Haute",
      "target_30d": 2026.62,
      "trend": "UP",
      "yhat": 2026.62,
      "yhat_lower": 1957.63,
      "yhat_upper": 2094.28,
      "train_start": "2023-05-24",
      "train_end": "2026-05-22",
      "train_rows": 578,
      "train_annualized_return": 0.4452
    },
    "NSBC_ci": {
      "ticker": "NSBC_ci",
      "last_price": 18000.0,
      "last_date": "2026-05-22",
      "signal": "VENTE",
      "confidence": "Haute",
      "target_30d": 16323.08,
      "trend": "DOWN",
      "yhat": 16323.08,
      "yhat_lower": 15878.42,
      "yhat_upper": 16754.9,
      "train_start": "2023-05-24",
      "train_end": "2026-05-22",
      "train_rows": 698,
      "train_annualized_return": 0.5182
    },
    "NTLC_ci": {
      "ticker": "NTLC_ci",
      "last_price": 13005.0,
      "last_date": "2026-05-22",
      "signal": "VENTE",
      "confidence": "Haute",
      "target_30d": 12520.32,
      "trend": "DOWN",
      "yhat": 12520.32,
      "yhat_lower": 12030.8,
      "yhat_upper": 13018.64,
      "train_start": "2023-05-24",
      "train_end": "2026-05-22",
      "train_rows": 651,
      "train_annualized_return": 0.1895
    },
    "ONTBF_bf": {
      "ticker": "ONTBF_bf",
      "last_price": 2850.0,
      "last_date": "2026-05-22",
      "signal": "NEUTRE",
      "confidence": "Haute",
      "target_30d": 2918.13,
      "trend": "UP",
      "yhat": 2918.13,
      "yhat_lower": 2812.98,
      "yhat_upper": 3024.62,
      "train_start": "2023-05-24",
      "train_end": "2026-05-22",
      "train_rows": 724,
      "train_annualized_return": -0.0058
    },
    "ORAC_ci": {
      "ticker": "ORAC_ci",
      "last_price": 15550.0,
      "last_date": "2026-05-22",
      "signal": "ACHAT",
      "confidence": "Haute",
      "target_30d": 16121.74,
      "trend": "UP",
      "yhat": 16121.74,
      "yhat_lower": 15659.52,
      "yhat_upper": 16566.33,
      "train_start": "2023-05-24",
      "train_end": "2026-05-22",
      "train_rows": 724,
      "train_annualized_return": 0.1808
    },
    "ORGT_tg": {
      "ticker": "ORGT_tg",
      "last_price": 2700.0,
      "last_date": "2026-05-22",
      "signal": "ACHAT FORT",
      "confidence": "Haute",
      "target_30d": 3353.07,
      "trend": "UP",
      "yhat": 3353.07,
      "yhat_lower": 3132.23,
      "yhat_upper": 3576.74,
      "train_start": "2023-05-24",
      "train_end": "2026-05-22",
      "train_rows": 662,
      "train_annualized_return": 0.0489
    },
    "PALC_ci": {
      "ticker": "PALC_ci",
      "last_price": 7680.0,
      "last_date": "2026-05-22",
      "signal": "NEUTRE",
      "confidence": "Haute",
      "target_30d": 7734.29,
      "trend": "UP",
      "yhat": 7734.29,
      "yhat_lower": 7354.32,
      "yhat_upper": 8105.63,
      "train_start": "2023-05-24",
      "train_end": "2026-05-22",
      "train_rows": 688,
      "train_annualized_return": -0.0775
    },
    "PRSC_ci": {
      "ticker": "PRSC_ci",
      "last_price": 4210.0,
      "last_date": "2026-05-22",
      "signal": "ACHAT FORT",
      "confidence": "Haute",
      "target_30d": 5248.63,
      "trend": "UP",
      "yhat": 5248.63,
      "yhat_lower": 4870.7,
      "yhat_upper": 5629.6,
      "train_start": "2023-05-30",
      "train_end": "2026-05-22",
      "train_rows": 664,
      "train_annualized_return": 0.1466
    },
    "SAFC_ci": {
      "ticker": "SAFC_ci",
      "last_price": 3700.0,
      "last_date": "2026-05-22",
      "signal": "ACHAT FORT",
      "confidence": "Moyenne",
      "target_30d": 5774.49,
      "trend": "UP",
      "yhat": 5774.49,
      "yhat_lower": 5284.78,
      "yhat_upper": 6295.38,
      "train_start": "2023-06-08",
      "train_end": "2026-05-22",
      "train_rows": 538,
      "train_annualized_return": 0.6648
    },
    "SCRC_ci": {
      "ticker": "SCRC_ci",
      "last_price": 2645.0,
      "last_date": "2026-05-22",
      "signal": "VENTE",
      "confidence": "Haute",
      "target_30d": 2462.46,
      "trend": "DOWN",
      "yhat": 2462.46,
      "yhat_lower": 2377.27,
      "yhat_upper": 2556.17,
      "train_start": "2023-05-30",
      "train_end": "2026-05-22",
      "train_rows": 674,
      "train_annualized_return": 0.6495
    },
    "SDCC_ci": {
      "ticker": "SDCC_ci",
      "last_price": 11095.0,
      "last_date": "2026-05-22",
      "signal": "VENTE FORTE",
      "confidence": "Haute",
      "target_30d": 9643.31,
      "trend": "DOWN",
      "yhat": 9643.31,
      "yhat_lower": 9294.71,
      "yhat_upper": 9982.21,
      "train_start": "2023-05-24",
      "train_end": "2026-05-22",
      "train_rows": 710,
      "train_annualized_return": 0.2939
    },
    "SDSC_ci": {
      "ticker": "SDSC_ci",
      "last_price": 1700.0,
      "last_date": "2026-05-22",
      "signal": "ACHAT",
      "confidence": "Haute",
      "target_30d": 1864.35,
      "trend": "UP",
      "yhat": 1864.35,
      "yhat_lower": 1748.34,
      "yhat_upper": 1978.94,
      "train_start": "2023-05-24",
      "train_end": "2026-05-22",
      "train_rows": 734,
      "train_annualized_return": 0.0682
    },
    "SEMC_ci": {
      "ticker": "SEMC_ci",
      "last_price": 1485.0,
      "last_date": "2026-05-22",
      "signal": "ACHAT FORT",
      "confidence": "Haute",
      "target_30d": 1917.11,
      "trend": "UP",
      "yhat": 1917.11,
      "yhat_lower": 1800.0,
      "yhat_upper": 2035.6,
      "train_start": "2026-01-02",
      "train_end": "2026-05-22",
      "train_rows": 101,
      "train_annualized_return": 4.9354
    },
    "SGBC_ci": {
      "ticker": "SGBC_ci",
      "last_price": 36000.0,
      "last_date": "2026-05-22",
      "signal": "ACHAT",
      "confidence": "Haute",
      "target_30d": 38467.61,
      "trend": "UP",
      "yhat": 38467.61,
      "yhat_lower": 37705.69,
      "yhat_upper": 39229.23,
      "train_start": "2023-05-24",
      "train_end": "2026-05-22",
      "train_rows": 715,
      "train_annualized_return": 0.3394
    },
    "SHEC_ci": {
      "ticker": "SHEC_ci",
      "last_price": 1935.0,
      "last_date": "2026-05-22",
      "signal": "ACHAT FORT",
      "confidence": "Haute",
      "target_30d": 2360.58,
      "trend": "UP",
      "yhat": 2360.58,
      "yhat_lower": 2282.19,
      "yhat_upper": 2445.35,
      "train_start": "2023-05-24",
      "train_end": "2026-05-22",
      "train_rows": 694,
      "train_annualized_return": 0.4141
    },
    "SIBC_ci": {
      "ticker": "SIBC_ci",
      "last_price": 8160.0,
      "last_date": "2026-05-22",
      "signal": "VENTE",
      "confidence": "Haute",
      "target_30d": 7736.27,
      "trend": "DOWN",
      "yhat": 7736.27,
      "yhat_lower": 7587.43,
      "yhat_upper": 7883.07,
      "train_start": "2023-05-24",
      "train_end": "2026-05-22",
      "train_rows": 736,
      "train_annualized_return": 0.4889
    },
    "SICC_ci": {
      "ticker": "SICC_ci",
      "last_price": 4400.0,
      "last_date": "2026-05-22",
      "signal": "VENTE",
      "confidence": "Moyenne",
      "target_30d": 4225.02,
      "trend": "DOWN",
      "yhat": 4225.02,
      "yhat_lower": 3887.89,
      "yhat_upper": 4583.46,
      "train_start": "2023-06-12",
      "train_end": "2026-05-22",
      "train_rows": 359,
      "train_annualized_return": -0.0922
    },
    "SIVC_ci": {
      "ticker": "SIVC_ci",
      "last_price": 2855.0,
      "last_date": "2026-05-22",
      "signal": "ACHAT FORT",
      "confidence": "Haute",
      "target_30d": 3460.47,
      "trend": "UP",
      "yhat": 3460.47,
      "yhat_lower": 3315.79,
      "yhat_upper": 3609.76,
      "train_start": "2023-06-01",
      "train_end": "2026-05-22",
      "train_rows": 566,
      "train_annualized_return": 0.6988
    },
    "SLBC_ci": {
      "ticker": "SLBC_ci",
      "last_price": 37945.0,
      "last_date": "2026-05-22",
      "signal": "ACHAT FORT",
      "confidence": "Haute",
      "target_30d": 46299.53,
      "trend": "UP",
      "yhat": 46299.53,
      "yhat_lower": 44454.24,
      "yhat_upper": 48173.85,
      "train_start": "2023-05-31",
      "train_end": "2026-05-22",
      "train_rows": 477,
      "train_annualized_return": 0.6937
    },
    "SMBC_ci": {
      "ticker": "SMBC_ci",
      "last_price": 12895.0,
      "last_date": "2026-05-22",
      "signal": "ACHAT",
      "confidence": "Haute",
      "target_30d": 13965.41,
      "trend": "UP",
      "yhat": 13965.41,
      "yhat_lower": 13240.44,
      "yhat_upper": 14706.82,
      "train_start": "2023-05-24",
      "train_end": "2026-05-22",
      "train_rows": 709,
      "train_annualized_return": 0.1786
    },
    "SNTS_sn": {
      "ticker": "SNTS_sn",
      "last_price": 28500.0,
      "last_date": "2026-05-22",
      "signal": "NEUTRE",
      "confidence": "Haute",
      "target_30d": 29324.41,
      "trend": "UP",
      "yhat": 29324.41,
      "yhat_lower": 28755.05,
      "yhat_upper": 29892.64,
      "train_start": "2023-05-24",
      "train_end": "2026-05-22",
      "train_rows": 650,
      "train_annualized_return": 0.2402
    },
    "SOGC_ci": {
      "ticker": "SOGC_ci",
      "last_price": 7390.0,
      "last_date": "2026-05-22",
      "signal": "ACHAT FORT",
      "confidence": "Haute",
      "target_30d": 8160.39,
      "trend": "UP",
      "yhat": 8160.39,
      "yhat_lower": 7854.8,
      "yhat_upper": 8502.23,
      "train_start": "2023-05-24",
      "train_end": "2026-05-22",
      "train_rows": 737,
      "train_annualized_return": 0.1392
    },
    "SPHC_ci": {
      "ticker": "SPHC_ci",
      "last_price": 6945.0,
      "last_date": "2026-05-22",
      "signal": "ACHAT",
      "confidence": "Haute",
      "target_30d": 7503.37,
      "trend": "UP",
      "yhat": 7503.37,
      "yhat_lower": 7169.79,
      "yhat_upper": 7864.12,
      "train_start": "2023-05-24",
      "train_end": "2026-05-22",
      "train_rows": 715,
      "train_annualized_return": 0.2021
    },
    "STAC_ci": {
      "ticker": "STAC_ci",
      "last_price": 2900.0,
      "last_date": "2026-05-22",
      "signal": "ACHAT FORT",
      "confidence": "Haute",
      "target_30d": 3376.19,
      "trend": "UP",
      "yhat": 3376.19,
      "yhat_lower": 3189.35,
      "yhat_upper": 3568.43,
      "train_start": "2023-05-30",
      "train_end": "2026-05-22",
      "train_rows": 584,
      "train_annualized_return": 0.3658
    },
    "STBC_ci": {
      "ticker": "STBC_ci",
      "last_price": 21275.0,
      "last_date": "2026-05-22",
      "signal": "ACHAT",
      "confidence": "Haute",
      "target_30d": 23043.6,
      "trend": "UP",
      "yhat": 23043.6,
      "yhat_lower": 22236.08,
      "yhat_upper": 23842.43,
      "train_start": "2023-05-24",
      "train_end": "2026-05-22",
      "train_rows": 629,
      "train_annualized_return": 0.486
    },
    "TTLC_ci": {
      "ticker": "TTLC_ci",
      "last_price": 2875.0,
      "last_date": "2026-05-22",
      "signal": "NEUTRE",
      "confidence": "Haute",
      "target_30d": 2831.71,
      "trend": "DOWN",
      "yhat": 2831.71,
      "yhat_lower": 2633.01,
      "yhat_upper": 3029.76,
      "train_start": "2023-05-24",
      "train_end": "2026-05-22",
      "train_rows": 726,
      "train_annualized_return": 0.1105
    },
    "TTLS_sn": {
      "ticker": "TTLS_sn",
      "last_price": 3195.0,
      "last_date": "2026-05-22",
      "signal": "ACHAT",
      "confidence": "Haute",
      "target_30d": 3505.21,
      "trend": "UP",
      "yhat": 3505.21,
      "yhat_lower": 3399.07,
      "yhat_upper": 3627.9,
      "train_start": "2023-05-24",
      "train_end": "2026-05-22",
      "train_rows": 721,
      "train_annualized_return": 0.0712
    },
    "UNLC_ci": {
      "ticker": "UNLC_ci",
      "last_price": 59000.0,
      "last_date": "2026-05-22",
      "signal": "ACHAT FORT",
      "confidence": "Moyenne",
      "target_30d": 71636.43,
      "trend": "UP",
      "yhat": 71636.43,
      "yhat_lower": 65368.94,
      "yhat_upper": 77852.67,
      "train_start": "2023-06-01",
      "train_end": "2026-05-22",
      "train_rows": 300,
      "train_annualized_return": 1.0838
    },
    "UNXC_ci": {
      "ticker": "UNXC_ci",
      "last_price": 1795.0,
      "last_date": "2026-05-22",
      "signal": "ACHAT FORT",
      "confidence": "Haute",
      "target_30d": 2145.63,
      "trend": "UP",
      "yhat": 2145.63,
      "yhat_lower": 2014.7,
      "yhat_upper": 2284.86,
      "train_start": "2023-05-24",
      "train_end": "2026-05-22",
      "train_rows": 703,
      "train_annualized_return": 0.4219
    }
  }
}